3_Base_of_Digital_Circuit/MultiAdder/Basic.v
module Basic;

  initial begin
    $dumpfile("wave.vcd");
    $dumpvars(0, Basic);
  end
  
  reg r_a;
  reg r_b;
  reg r_x;


  wire [1:0] w_add;
  
  assign w_add = r_a + r_b + r_x;

  initial begin
    r_a = 1'b0;
    r_b = 1'b0;
    r_x = 1'b0;
    #2
    r_a = 1'b1;
    r_b = 1'b0;
    r_x = 1'b0;
    #2
    r_a = 1'b0;
    r_b = 1'b1;
    r_x = 1'b0;
    #2
    r_a = 1'b1;
    r_b = 1'b1;
    r_x = 1'b0;
    #2
    r_a = 1'b0;
    r_b = 1'b0;
    r_x = 1'b1;
    #2
    r_a = 1'b1;
    r_b = 1'b0;
    r_x = 1'b1;
    #2
    r_a = 1'b0;
    r_b = 1'b1;
    r_x = 1'b1;
    #2
    r_a = 1'b1;
    r_b = 1'b1;
    r_x = 1'b1;
    #2
    $finish;
  end

endmodule

3_Base_of_Digital_Circuit/MultiAdder/wave.vcd
$date
	Mon May  6 17:09:32 2024
$end
$version
	Icarus Verilog
$end
$timescale
	1s
$end
$scope module Basic $end
$var wire 2 ! w_add [1:0] $end
$var reg 1 " r_a $end
$var reg 1 # r_b $end
$var reg 1 $ r_x $end
$upscope $end
$enddefinitions $end
$comment Show the parameter values. $end
$dumpall
$end
#0
$dumpvars
0$
0#
0"
b0 !
$end
#2
b1 !
1"
#4
1#
b1 !
0"
#6
b10 !
1"
#8
1$
0#
b1 !
0"
#10
b10 !
1"
#12
1#
b10 !
0"
#14
b11 !
1"
