3_Base_of_Digital_Circuit/FullAdder/Basic.v
module Basic;

  initial begin
    $dumpfile("wave.vcd");
    $dumpvars(0, Basic);
  end
  
  reg r_a;
  reg r_b;
  reg r_x;

  wire w_c;
  wire w_s;
  wire w_c_ab;
  wire w_s_ab;
  wire w_c_abx;

  assign w_c_ab = r_a & r_b;
  assign w_s_ab = r_a ^ r_b;

  assign w_c_abx = w_s_ab & r_x;
  assign w_s = w_s_ab ^ r_x;
  
  assign w_c = w_c_ab | w_c_abx;

  initial begin
    r_a = 1'b0;
    r_b = 1'b0;
    r_x = 1'b0;
    #2
    r_a = 1'b1;
    r_b = 1'b0;
    r_x = 1'b0;
    #2
    r_a = 1'b0;
    r_b = 1'b1;
    r_x = 1'b0;
    #2
    r_a = 1'b1;
    r_b = 1'b1;
    r_x = 1'b0;
    #2
    r_a = 1'b0;
    r_b = 1'b0;
    r_x = 1'b1;
    #2
    r_a = 1'b1;
    r_b = 1'b0;
    r_x = 1'b1;
    #2
    r_a = 1'b0;
    r_b = 1'b1;
    r_x = 1'b1;
    #2
    r_a = 1'b1;
    r_b = 1'b1;
    r_x = 1'b1;
    #2
    $finish;
  end

endmodule

3_Base_of_Digital_Circuit/FullAdder/wave.vcd
$date
	Mon May  6 17:00:31 2024
$end
$version
	Icarus Verilog
$end
$timescale
	1s
$end
$scope module Basic $end
$var wire 1 ! w_c $end
$var wire 1 " w_c_ab $end
$var wire 1 # w_c_abx $end
$var wire 1 $ w_s $end
$var wire 1 % w_s_ab $end
$var reg 1 & r_a $end
$var reg 1 ' r_b $end
$var reg 1 ( r_x $end
$upscope $end
$enddefinitions $end
$comment Show the parameter values. $end
$dumpall
$end
#0
$dumpvars
0(
0'
0&
0%
0$
0#
0"
0!
$end
#2
1$
1%
1&
#4
1'
0&
#6
0$
1!
0%
1"
1&
#8
0!
1$
0"
1(
0'
0&
#10
1!
1#
0$
1%
1&
#12
1'
0&
#14
0#
1$
0%
1"
1&
