3_Base_of_Digital_Circuit/MUX/Basic.v
module Basic;

  initial begin
    $dumpfile("wave.vcd");
    $dumpvars(0, Basic);
  end
  
  reg r_a;
  reg r_b;
  reg r_s;

  wire w_x;

  //assign w_x = (r_a & ~r_s) | (r_b & r_s);
  assign w_x = r_s ? r_b : r_a;

  initial begin
    r_a = 1'b0;
    r_b = 1'b0;
    r_s = 1'b0;
    #2
    r_a = 1'b1;
    r_b = 1'b0;
    r_s = 1'b0;
    #2
    r_a = 1'b0;
    r_b = 1'b1;
    r_s = 1'b0;
    #2
    r_a = 1'b1;
    r_b = 1'b1;
    r_s = 1'b0;
    #2
    r_a = 1'b0;
    r_b = 1'b0;
    r_s = 1'b1;
    #2
    r_a = 1'b1;
    r_b = 1'b0;
    r_s = 1'b1;
    #2
    r_a = 1'b0;
    r_b = 1'b1;
    r_s = 1'b1;
    #2
    r_a = 1'b1;
    r_b = 1'b1;
    r_s = 1'b1;
    #2
    $finish;
  end

endmodule

3_Base_of_Digital_Circuit/MUX/wave.vcd
$date
	Mon May  6 16:37:36 2024
$end
$version
	Icarus Verilog
$end
$timescale
	1s
$end
$scope module Basic $end
$var wire 1 ! w_x $end
$var reg 1 " r_a $end
$var reg 1 # r_b $end
$var reg 1 $ r_s $end
$upscope $end
$enddefinitions $end
$comment Show the parameter values. $end
$dumpall
$end
#0
$dumpvars
0$
0#
0"
0!
$end
#2
1!
1"
#4
0!
1#
0"
#6
1!
1"
#8
0!
1$
0#
0"
#10
1"
#12
1!
1#
0"
#14
1"
