4_Stricturing_Digital_Circuits/HalfAdder.v
module HalfAdder(
  input i_a,
  input i_b,
  output o_c,
  output o_s
);

  assign o_c = i_a & i_b;
  assign o_s = i_a ^ i_b;

endmodule

4_Stricturing_Digital_Circuits/FullAdder.v
module FullAdder(
  input i_a,
  input i_b,
  input i_x,
  output o_c,
  output o_s
);

  wire w_c_ab;
  wire w_s_ab;
  wire w_c_abx;

  assign w_c_ab = i_a & i_b;
  assign w_s_ab = i_a ^ i_b;

  assign w_c_abx = w_s_ab & i_x;
  assign o_s     = w_s_ab ^ i_x;

  HalfAdder HA1 (
    .i_a    (i_a    ),
    .i_b    (i_b    ),
    .o_c    (w_c_ab ),
    .o_s    (w_s_ab )
  );

  HalfAdder HA2 (
    .i_a    (w_s_ab ),
    .i_b    (i_x    ),
    .o_c    (w_c_abx),
    .o_s    (o_s    )
  );
  
  assign o_c = w_c_ab | w_c_abx;

endmodule

4_Stricturing_Digital_Circuits/Basic.v
module Basic;

  initial begin
    $dumpfile("wave.vcd");
    $dumpvars(0, Basic);
  end
  
  reg r_a;
  reg r_b;
  reg r_x;


  wire w_c;
  wire w_s;

  FullAdder FA (
    .i_a    (r_a    ),
    .i_b    (r_b    ),
    .i_x    (r_x    ),
    .o_c    (w_c    ),
    .o_s    (w_s    )
  );

  initial begin
    r_a = 1'b0;
    r_b = 1'b0;
    r_x = 1'b0;
    #2
    r_a = 1'b1;
    r_b = 1'b0;
    r_x = 1'b0;
    #2
    r_a = 1'b0;
    r_b = 1'b1;
    r_x = 1'b0;
    #2
    r_a = 1'b1;
    r_b = 1'b1;
    r_x = 1'b0;
    #2
    r_a = 1'b0;
    r_b = 1'b0;
    r_x = 1'b1;
    #2
    r_a = 1'b1;
    r_b = 1'b0;
    r_x = 1'b1;
    #2
    r_a = 1'b0;
    r_b = 1'b1;
    r_x = 1'b1;
    #2
    r_a = 1'b1;
    r_b = 1'b1;
    r_x = 1'b1;
    #2
    $finish;
  end

endmodule

4_Stricturing_Digital_Circuits/wave.vcd
$date
	Mon May  6 18:14:40 2024
$end
$version
	Icarus Verilog
$end
$timescale
	1s
$end
$scope module Basic $end
$var wire 1 ! w_s $end
$var wire 1 " w_c $end
$var reg 1 # r_a $end
$var reg 1 $ r_b $end
$var reg 1 % r_x $end
$scope module FA $end
$var wire 1 # i_a $end
$var wire 1 $ i_b $end
$var wire 1 % i_x $end
$var wire 1 " o_c $end
$var wire 1 ! o_s $end
$var wire 1 & w_c_ab $end
$var wire 1 ' w_c_abx $end
$var wire 1 ( w_s_ab $end
$scope module HA1 $end
$var wire 1 # i_a $end
$var wire 1 $ i_b $end
$var wire 1 & o_c $end
$var wire 1 ( o_s $end
$upscope $end
$scope module HA2 $end
$var wire 1 ( i_a $end
$var wire 1 % i_b $end
$var wire 1 ' o_c $end
$var wire 1 ! o_s $end
$upscope $end
$upscope $end
$upscope $end
$enddefinitions $end
$comment Show the parameter values. $end
$dumpall
$end
#0
$dumpvars
0(
0'
0&
0%
0$
0#
0"
0!
$end
#2
1!
1(
1#
#4
1$
0#
#6
1"
0!
1&
0(
1#
#8
0"
1!
0&
1%
0$
0#
#10
1"
1'
0!
1(
1#
#12
1$
0#
#14
0'
1!
1&
0(
1#
